oneservice/__init__.py
oneservice-1.0.0.dist-info/entry_points.txt
oneservice-1.0.0.dist-info/LICENSE.md
oneservice-1.0.0.dist-info/WHEEL
oneservice-1.0.0.dist-info/METADATA
oneservice-1.0.0.dist-info/RECORD
