Metadata-Version: 2.1
Name: oneservice
Version: 1.0.0
Summary: Wrapper around Flask aimed at conveniently creating microservices
Home-page: https://gitlab.com/davidevi/oneservice
License: MIT
Keywords: microservice,micro,service,oneservice,one
Author: Davide Vitelaru
Author-email: davide@vitelaru.com
Requires-Python: >=3.7,<4.0
Classifier: License :: OSI Approved :: MIT License
Classifier: Programming Language :: Python :: 3
Classifier: Programming Language :: Python :: 3.7
Classifier: Programming Language :: Python :: 3.8
Requires-Dist: flask (>=1.1.2,<2.0.0)
Project-URL: Repository, https://gitlab.com/davidevi/oneservice
